Tclpy/__init__.py
Tclpy/setup.py
Tclpy-0.1.dist-info/METADATA
Tclpy-0.1.dist-info/WHEEL
Tclpy-0.1.dist-info/top_level.txt
Tclpy-0.1.dist-info/RECORD
