Metadata-Version: 2.1
Name: Tclpy
Version: 0.1
Summary: Tkinter in python might not work if not in bash.
Home-page: UNKNOWN
Author: Robert
Author-email: xsumagravity@gmail.com
License: UNKNOWN
Platform: UNKNOWN
Classifier: Programming Language :: Python :: 3
Classifier: License :: OSI Approved :: MIT License
Classifier: Operating System :: MacOS
